agent_transparency-0.0.1.dist-info/licenses/LICENSE
transparency/__init__.py
transparency/__main__.py
transparency/transparency.py
transparency/types.py
viewer/viewer.html
viewer/viewer_server.py
agent_transparency-0.0.1.dist-info/METADATA
agent_transparency-0.0.1.dist-info/WHEEL
agent_transparency-0.0.1.dist-info/entry_points.txt
agent_transparency-0.0.1.dist-info/top_level.txt
agent_transparency-0.0.1.dist-info/RECORD
