Metadata-Version: 2.4
Name: agent-transparency
Version: 0.0.1
Summary: A comprehensive library for tracking the input, thought process, and output of AI agents
Author-email: Agent Squad <shine.six.s6@gamil.com>
License: MIT
Project-URL: Homepage, https://github.com/agentsquad/transparency
Project-URL: Documentation, https://github.com/agentsquad/transparency#readme
Project-URL: Repository, https://github.com/agentsquad/transparency
Project-URL: Issues, https://github.com/agentsquad/transparency/issues
Keywords: agent,transparency,logging,ai,observability
Classifier: Development Status :: 4 - Beta
Classifier: Intended Audience :: Developers
Classifier: License :: OSI Approved :: MIT License
Classifier: Programming Language :: Python :: 3
Classifier: Programming Language :: Python :: 3.12
Classifier: Topic :: Software Development :: Libraries :: Python Modules
Classifier: Topic :: System :: Logging
Requires-Python: >=3.12
License-File: LICENSE
Requires-Dist: build>=1.4.0
Requires-Dist: twine>=6.2.0
Provides-Extra: ui
Requires-Dist: aiohttp>=3.8.0; extra == "ui"
Provides-Extra: kafka
Requires-Dist: aiokafka>=0.8.0; extra == "kafka"
Provides-Extra: dev
Requires-Dist: pytest>=7.0.0; extra == "dev"
Requires-Dist: pytest-asyncio>=0.21.0; extra == "dev"
Requires-Dist: black>=23.0.0; extra == "dev"
Requires-Dist: mypy>=1.0.0; extra == "dev"
Requires-Dist: ruff>=0.1.0; extra == "dev"
Provides-Extra: all
Requires-Dist: aiohttp>=3.8.0; extra == "all"
Requires-Dist: aiokafka>=0.8.0; extra == "all"
Dynamic: license-file
